{
    "krajiny": [
    {"názov": "Albánsko", "vlajka": "./flags/albansko.png"},
    {"názov": "Andorra", "vlajka": "./flags/andorra.png"},
    {"názov": "Bielorusko", "vlajka": "./flags/bielorusko.png"},
    {"názov": "Belgicko", "vlajka": "./flags/belgicko.png"},
    {"názov": "Bosna a Hercegovina", "vlajka": "./flags/bosna.png"},
    {"názov": "Bulharsko", "vlajka": "./flags/bulharsko.png"},
    {"názov": "Cyprus", "vlajka": "./flags/cyprus.png"},
    {"názov": "Česká republika", "vlajka": "./flags/cesko.png"},
    {"názov": "Čierna Hora", "vlajka": "./flags/ciernahora.png"},
    {"názov": "Chorvátsko", "vlajka": "./flags/chorvatsko.png"},
    {"názov": "Dánsko", "vlajka": "./flags/dansko.png"},
    {"názov": "Estónsko", "vlajka": "./flags/estonsko.png"},
    {"názov": "Fínsko", "vlajka": "./flags/finsko.png"},
    {"názov": "Francúzsko", "vlajka": "./flags/francuzsko.png"},
    {"názov": "Grécko", "vlajka": "./flags/grecko.png"},
    {"názov": "Holandsko", "vlajka": "./flags/holandsko.png"},
    {"názov": "Írsko", "vlajka": "./flags/irsko.png"},
    {"názov": "Island", "vlajka": "./flags/island.png"},
    {"názov": "Kosovo", "vlajka": "./flags/kosovo.png"},
    {"názov": "Lichtenštajnsko", "vlajka": "./flags/lichtenstajnsko.png"},
    {"názov": "Litva", "vlajka": "./flags/litva.png"},
    {"názov": "Lotyšsko", "vlajka": "./flags/lotyssko.png"},
    {"názov": "Luxembursko", "vlajka": "./flags/luxembursko.png"},
    {"názov": "Maďarsko", "vlajka": "./flags/madarsko.png"},
    {"názov": "Macedonsko", "vlajka": "./flags/macedonsko.png"},
    {"názov": "Malta", "vlajka": "./flags/malta.png"},
    {"názov": "Moldavsko", "vlajka": "./flags/moldavsko.png"},
    {"názov": "Monako", "vlajka": "./flags/monako.png"},
    {"názov": "Nemecko", "vlajka": "./flags/nemecko.png"},
    {"názov": "Nórsko", "vlajka": "./flags/norsko.png"},
    {"názov": "Poľsko", "vlajka": "./flags/polsko.png"},
    {"názov": "Portugalsko", "vlajka": "./flags/portugalsko.png"},
    {"názov": "Rakúsko", "vlajka": "./flags/rakusko.png"},
    {"názov": "Rumunsko", "vlajka": "./flags/rumunsko.png"},
    {"názov": "Rusko", "vlajka": "./flags/rusko.png"},
    {"názov": "San Maríno", "vlajka": "./flags/sanmarino.png"},
    {"názov": "Srbsko", "vlajka": "./flags/srbsko.png"},
    {"názov": "Slovensko", "vlajka": "./flags/slovensko.png"},
    {"názov": "Slovinsko", "vlajka": "./flags/slovinsko.png"},
    {"názov": "Španielsko", "vlajka": "./flags/spanielsko.png"},
    {"názov": "Švajčiarsko", "vlajka": "./flags/svajciarsko.png"},
    {"názov": "Švédsko", "vlajka": "./flags/svedsko.png"},
    {"názov": "Taliansko", "vlajka": "./flags/taliansko.png"},
    {"názov": "Turecko", "vlajka": "./flags/turecko.png"},
    {"názov": "Ukrajina", "vlajka": "./flags/ukrajina.png"},
    {"názov": "Vatikán", "vlajka": "./flags/vatikán.png"},
    {"názov": "Veľká Británia", "vlajka": "./flags/velkabritania.png"}
    ]
    }